LICENSE
MANIFEST.in
README.rst
setup.py
il2fb/regiments/__init__.py
il2fb/regiments/data/regInfo_en.properties
il2fb/regiments/data/regInfo_ru.properties
il2fb/regiments/data/regShort_en.properties
il2fb/regiments/data/regShort_ru.properties
il2fb/regiments/data/regiments.ini
il2fb_regiments.egg-info/PKG-INFO
il2fb_regiments.egg-info/SOURCES.txt
il2fb_regiments.egg-info/dependency_links.txt
il2fb_regiments.egg-info/namespace_packages.txt
il2fb_regiments.egg-info/requires.txt
il2fb_regiments.egg-info/top_level.txt
requirements/dist.txt